pythonosc/__init__.py
pythonosc/dispatcher.py
pythonosc/osc_bundle.py
pythonosc/osc_bundle_builder.py
pythonosc/osc_message.py
pythonosc/osc_message_builder.py
pythonosc/osc_packet.py
pythonosc/osc_server.py
pythonosc/osc_tcp_server.py
pythonosc/slip.py
pythonosc/tcp_client.py
pythonosc/udp_client.py
pythonosc/parsing/__init__.py
pythonosc/parsing/ntp.py
pythonosc/parsing/osc_types.py
pythonosc/test/__init__.py
pythonosc/test/test_dispatcher.py
pythonosc/test/test_osc_bundle.py
pythonosc/test/test_osc_bundle_builder.py
pythonosc/test/test_osc_message.py
pythonosc/test/test_osc_message_builder.py
pythonosc/test/test_osc_packet.py
pythonosc/test/test_osc_server.py
pythonosc/test/test_osc_tcp_server.py
pythonosc/test/test_tcp_client.py
pythonosc/test/test_udp_client.py
pythonosc/test/parsing/__init__.py
pythonosc/test/parsing/test_ntp.py
pythonosc/test/parsing/test_osc_types.py
python_osc-1.9.2.dist-info/LICENSE.txt
python_osc-1.9.2.dist-info/METADATA
python_osc-1.9.2.dist-info/WHEEL
python_osc-1.9.2.dist-info/top_level.txt
python_osc-1.9.2.dist-info/RECORD
