Metadata-Version: 2.1
Name: python-osc
Version: 1.9.2
Summary: Open Sound Control server and client implementations in pure Python
Author-email: attwad <tmusoft@gmail.com>
License: This is free and unencumbered software released into the public domain.
Project-URL: Repository, https://github.com/attwad/python-osc
Keywords: osc,sound,midi,music
Classifier: Development Status :: 5 - Production/Stable
Classifier: Intended Audience :: Developers
Classifier: License :: Freely Distributable
Classifier: Programming Language :: Python :: 3
Classifier: Topic :: Multimedia :: Sound/Audio
Classifier: Topic :: System :: Networking
Requires-Python: >=3.10
License-File: LICENSE.txt
